tidyname/__init__.py
tidyname/cleaner.py
tidyname/logic.py
tidyname/py.typed
tidyname/terms.py
tidyname/types.py
tidyname-0.1.0.dist-info/licenses/LICENSE
tidyname-0.1.0.dist-info/METADATA
tidyname-0.1.0.dist-info/WHEEL
tidyname-0.1.0.dist-info/top_level.txt
tidyname-0.1.0.dist-info/RECORD
