Metadata-Version: 2.4
Name: tidyname
Version: 0.1.0
Summary: Intelligent company name cleaning for Python
Author-email: Michelle Pellon <mgracepellon@gmail.com>
License-Expression: MIT
Project-URL: Homepage, https://github.com/michellepellon/tidyname
Project-URL: Repository, https://github.com/michellepellon/tidyname
Project-URL: Issues, https://github.com/michellepellon/tidyname/issues
Keywords: company,name,cleaning,normalization,nlp
Classifier: Development Status :: 5 - Production/Stable
Classifier: Intended Audience :: Developers
Classifier: Programming Language :: Python :: 3
Classifier: Programming Language :: Python :: 3.13
Classifier: Topic :: Software Development :: Libraries :: Python Modules
Classifier: Topic :: Text Processing :: Linguistic
Requires-Python: >=3.13
License-File: LICENSE
Dynamic: license-file
